animeflv/__init__.py
animeflv/animeflv.py
animeflv/exception.py
animeflv-0.3.0.dist-info/LICENSE
animeflv-0.3.0.dist-info/METADATA
animeflv-0.3.0.dist-info/WHEEL
animeflv-0.3.0.dist-info/top_level.txt
animeflv-0.3.0.dist-info/RECORD
