Metadata-Version: 2.1
Name: animeflv
Version: 0.3.0
Summary: AnimeFLV is a python custom API for https://animeflv.net website
Author-email: Jorge Alejandro Jiménez Luna <jorgeajimenezl17@gmail.com>
License: MIT License
Keywords: animeflv,anime,manga
Classifier: Intended Audience :: Developers
Classifier: License :: OSI Approved :: MIT License
Classifier: Operating System :: OS Independent
Classifier: Programming Language :: Python
Classifier: Programming Language :: Python :: 3.5
Classifier: Programming Language :: Python :: 3.6
Classifier: Programming Language :: Python :: 3.7
Classifier: Programming Language :: Python :: 3.8
Classifier: Programming Language :: Python :: 3.9
Classifier: Programming Language :: Python :: 3.10
Classifier: Programming Language :: Python :: 3.11
Requires-Python: >=3.5
License-File: LICENSE
